{
    "last_updated": "2026-01-13 12:20:31",
    "date": "2026-01-13",
    "nyt_games": {
        "spelling_bee": {
            "center": "M",
            "letters": "EILNTY",
            "pangrams": [
                "IMMINENTLY",
                "EMINENTLY"
            ]
        },
        "strands": {
            "theme": "You need to chill",
            "spangram": "FROZENFOOD"
        }
    },
    "la_times": {
        "status": "Failed to fetch LA Times answers"
    },
    "status": "All Systems Go"
}